{"tasks":[{"id":"084fd0b2-bf1a-4560-80ec-c3361f4f9e86","title":"Validação de id em put","description":"Retornar 404 se não encontrar","created_at":"2026-02-02T21:11:38.532Z","updated_at":"2026-02-02T23:49:54.425Z","completed_at":null},{"id":"7c635cb7-f9fa-4822-9678-1b80689b41d0","title":"crud","description":"implementar tarefas","created_at":"2026-02-02T21:11:50.331Z","updated_at":"2026-02-02T21:11:50.331Z","completed_at":null},{"id":"8556ea6a-517b-4a04-9ade-3e3bdd150bc7","title":"Modulo 2 de Node","description":"assistir aulas","created_at":"2026-02-02T21:13:17.263Z","updated_at":"2026-02-02T23:20:58.684Z","completed_at":null},{"id":"9db410db-f21c-47e6-b09a-089ab2f44a51","title":"Rota PUT","description":"Acabar implementação da rota PUT","updated_at":"2026-02-02T22:42:09.158Z"},{"id":"3a20c1d6-6aeb-4272-ae14-857bb4cb1093","title":"Implementar rota delete","description":"Deletar por id","created_at":"2026-02-02T22:44:41.194Z","updated_at":"2026-02-02T22:44:41.194Z","completed_at":null}]}